{
    "added": {
        "110224": "大兴县",
        "110226": "平谷县",
        "110227": "怀柔县",
        "120224": "宝坻县",
        "152100": "呼伦贝尔盟",
        "152101": "海拉尔市",
        "152700": "伊克昭盟",
        "152701": "东胜市",
        "310225": "南汇县",
        "310226": "奉贤县",
        "320704": "云台区",
        "330181": "萧山市",
        "330184": "余杭市",
        "330821": "衢县",
        "340505": "向山区",
        "370123": "长清县",
        "420203": "石灰窑区",
        "420521": "宜昌县",
        "420621": "襄阳县",
        "430403": "城南区",
        "440421": "斗门县",
        "460001": "通什市",
        "500221": "长寿县",
        "510125": "新都县",
        "532100": "昭通地区",
        "533421": "中甸县",
        "612500": "商洛地区",
        "612501": "商州市",
        "622300": "武威地区",
        "642200": "固原地区",
        "642221": "固原县",
        "654100": "伊犁地区"
    },
    "deleted": {
        "110115": "大兴区",
        "110116": "怀柔区",
        "110117": "平谷区",
        "120115": "宝坻区",
        "130108": "裕华区",
        "150600": "鄂尔多斯市",
        "150602": "东胜区",
        "150700": "呼伦贝尔市",
        "150702": "海拉尔区",
        "310119": "南汇区",
        "310120": "奉贤区",
        "330109": "萧山区",
        "330110": "余杭区",
        "330803": "衢江区",
        "370113": "长清区",
        "410611": "淇滨区",
        "420203": "西塞山区",
        "420506": "夷陵区",
        "420607": "襄阳区",
        "420804": "掇刀区",
        "430405": "珠晖区",
        "430406": "雁峰区",
        "430407": "石鼓区",
        "430408": "蒸湘区",
        "440403": "斗门区",
        "440404": "金湾区",
        "440903": "茂港区",
        "460001": "五指山市",
        "500115": "长寿区",
        "510114": "新都区",
        "530602": "昭阳区",
        "533421": "香格里拉县",
        "611000": "商洛市",
        "611002": "商州区",
        "620602": "凉州区",
        "640400": "固原市",
        "640402": "原州区"
    }
}